{
  "inputs": [
    {
      "name": "texture",
      "filename": "texture_1920x1080.yuv",
      "width": 1920,
      "height": 1080
    },
    {
      "name": "alpha",
      "filename": "alpha_1920x1080.yuv",
      "width": 1920,
      "height": 1080
    }
  ],
  "xlayers": [
    {
      "xlayer_id": 0,
      "input_source": "texture",
      "width": 960,
      "height": 540,
      "profile": 3,
      "level": 12,
      "tier": 0,
      "layer_type": "texture",
      "num_temporal_layers": 1,
      "num_embedded_layers": 1,
      "qp": 128,
      "cpu_used": 9,
      "lag_in_frames": 0,
      "atlas_pos_x": 0,
      "atlas_pos_y": 0
    },
    {
      "xlayer_id": 1,
      "input_source": "texture",
      "width": 960,
      "height": 540,
      "profile": 3,
      "level": 12,
      "tier": 0,
      "layer_type": "texture",
      "num_temporal_layers": 1,
      "num_embedded_layers": 1,
      "qp": 128,
      "cpu_used": 9,
      "lag_in_frames": 0,
      "atlas_pos_x": 960,
      "atlas_pos_y": 0
    },
    {
      "xlayer_id": 2,
      "input_source": "alpha",
      "width": 960,
      "height": 540,
      "profile": 3,
      "level": 12,
      "tier": 0,
      "layer_type": "auxiliary",
      "auxiliary_type": "alpha",
      "num_temporal_layers": 1,
      "num_embedded_layers": 1,
      "qp": 128,
      "cpu_used": 9,
      "lag_in_frames": 0,
      "atlas_pos_x": 0,
      "atlas_pos_y": 0
    },
    {
      "xlayer_id": 3,
      "input_source": "alpha",
      "width": 960,
      "height": 540,
      "profile": 3,
      "level": 12,
      "tier": 0,
      "layer_type": "auxiliary",
      "auxiliary_type": "alpha",
      "num_temporal_layers": 1,
      "num_embedded_layers": 1,
      "qp": 128,
      "cpu_used": 9,
      "lag_in_frames": 0,
      "atlas_pos_x": 960,
      "atlas_pos_y": 0
    }
  ],
  "global_lcr": {
    "enable": true,
    "purpose_id": 0,
    "dependent_xlayers": false,
    "doh_constraint": true
  },
  "msdo": {
    "enable": false
  },
  "ops": [
    {
      "ops_id": 0,
      "priority": 0,
      "intent_present": true,
      "ptl_present": true,
      "operating_points": [
        {
          "intent": 0,
          "xlayer_map": [0, 1],
          "comment": "OP0: texture only"
        },
        {
          "intent": 1,
          "xlayer_map": [0, 1, 2, 3],
          "comment": "OP1: texture + alpha"
        }
      ]
    }
  ],
  "atlas": {
    "enable": true,
    "mode": 0,
    "width": 1920,
    "height": 1080,
    "uniform_spacing": false
  },
  "combined_tu": true,
  "monotonic_output_order": true,
  "output": "subpic_tex_alpha_muxed.obu"
}
